[
    {
        "club_id": "20098",
        "escudo_url": "https://www.cbf.com.br/_next/image?url=https%3A%2F%2Fconteudo.cbf.com.br%2Fclubes%2F20098%2Fescudo.jpg&w=256&q=70",
        "time": "Gama - DF",
        "pontos": 32,
        "jogos": 13,
        "vitorias": 10,
        "empates": 2,
        "derrotas": 1,
        "gols_pro": 26,
        "gols_contra": 9,
        "saldo_gols": 17,
        "fase_nivel": 3,
        "status": "3ª Fase"
    },
    {
        "club_id": "62025",
        "escudo_url": "https://www.cbf.com.br/_next/image?url=https%3A%2F%2Fconteudo.cbf.com.br%2Fclubes%2F62025%2Fescudo.jpg&w=256&q=70",
        "time": "America - RJ",
        "pontos": 30,
        "jogos": 13,
        "vitorias": 9,
        "empates": 3,
        "derrotas": 1,
        "gols_pro": 22,
        "gols_contra": 4,
        "saldo_gols": 18,
        "fase_nivel": 3,
        "status": "3ª Fase"
    },
    {
        "club_id": "63521",
        "escudo_url": "https://www.cbf.com.br/_next/image?url=https%3A%2F%2Fconteudo.cbf.com.br%2Fclubes%2F63521%2Fescudo.jpg&w=256&q=70",
        "time": "Portuguesa - SP",
        "pontos": 29,
        "jogos": 14,
        "vitorias": 8,
        "empates": 5,
        "derrotas": 1,
        "gols_pro": 21,
        "gols_contra": 8,
        "saldo_gols": 13,
        "fase_nivel": 3,
        "status": "3ª Fase"
    },
    {
        "club_id": "59102",
        "escudo_url": "https://www.cbf.com.br/_next/image?url=https%3A%2F%2Fconteudo.cbf.com.br%2Fclubes%2F59102%2Fescudo.jpg&w=256&q=70",
        "time": "Manauara - AM",
        "pontos": 29,
        "jogos": 13,
        "vitorias": 8,
        "empates": 5,
        "derrotas": 0,
        "gols_pro": 17,
        "gols_contra": 6,
        "saldo_gols": 11,
        "fase_nivel": 3,
        "status": "3ª Fase"
    },
    {
        "club_id": "37743",
        "escudo_url": "https://www.cbf.com.br/_next/image?url=https%3A%2F%2Fconteudo.cbf.com.br%2Fclubes%2F37743%2Fescudo.jpg&w=256&q=70",
        "time": "Capital - TO",
        "pontos": 27,
        "jogos": 13,
        "vitorias": 8,
        "empates": 3,
        "derrotas": 2,
        "gols_pro": 21,
        "gols_contra": 8,
        "saldo_gols": 13,
        "fase_nivel": 3,
        "status": "3ª Fase"
    },
    {
        "club_id": "20042",
        "escudo_url": "https://www.cbf.com.br/_next/image?url=https%3A%2F%2Fconteudo.cbf.com.br%2Fclubes%2F20042%2Fescudo.jpg&w=256&q=70",
        "time": "ABC - RN",
        "pontos": 27,
        "jogos": 13,
        "vitorias": 8,
        "empates": 3,
        "derrotas": 2,
        "gols_pro": 18,
        "gols_contra": 9,
        "saldo_gols": 9,
        "fase_nivel": 3,
        "status": "3ª Fase"
    },
    {
        "club_id": "20050",
        "escudo_url": "https://www.cbf.com.br/_next/image?url=https%3A%2F%2Fconteudo.cbf.com.br%2Fclubes%2F20050%2Fescudo.jpg&w=256&q=70",
        "time": "Nacional - AM",
        "pontos": 27,
        "jogos": 13,
        "vitorias": 8,
        "empates": 3,
        "derrotas": 2,
        "gols_pro": 17,
        "gols_contra": 9,
        "saldo_gols": 8,
        "fase_nivel": 3,
        "status": "3ª Fase"
    },
    {
        "club_id": "35361",
        "escudo_url": "https://www.cbf.com.br/_next/image?url=https%3A%2F%2Fconteudo.cbf.com.br%2Fclubes%2F35361%2Fescudo.jpg&w=256&q=70",
        "time": "Iguatu - CE",
        "pontos": 27,
        "jogos": 13,
        "vitorias": 7,
        "empates": 6,
        "derrotas": 0,
        "gols_pro": 20,
        "gols_contra": 11,
        "saldo_gols": 9,
        "fase_nivel": 3,
        "status": "3ª Fase"
    },
    {
        "club_id": "20091",
        "escudo_url": "https://www.cbf.com.br/_next/image?url=https%3A%2F%2Fconteudo.cbf.com.br%2Fclubes%2F20091%2Fescudo.jpg&w=256&q=70",
        "time": "Ferroviário - CE",
        "pontos": 26,
        "jogos": 13,
        "vitorias": 7,
        "empates": 5,
        "derrotas": 1,
        "gols_pro": 19,
        "gols_contra": 9,
        "saldo_gols": 10,
        "fase_nivel": 3,
        "status": "3ª Fase"
    },
    {
        "club_id": "20045",
        "escudo_url": "https://www.cbf.com.br/_next/image?url=https%3A%2F%2Fconteudo.cbf.com.br%2Fclubes%2F20045%2Fescudo.jpg&w=256&q=70",
        "time": "CSA - AL",
        "pontos": 25,
        "jogos": 13,
        "vitorias": 7,
        "empates": 4,
        "derrotas": 2,
        "gols_pro": 28,
        "gols_contra": 10,
        "saldo_gols": 18,
        "fase_nivel": 3,
        "status": "3ª Fase"
    },
    {
        "club_id": "53757",
        "escudo_url": "https://www.cbf.com.br/_next/image?url=https%3A%2F%2Fconteudo.cbf.com.br%2Fclubes%2F53757%2Fescudo.jpg&w=256&q=70",
        "time": "Guaporé - RO",
        "pontos": 25,
        "jogos": 13,
        "vitorias": 7,
        "empates": 4,
        "derrotas": 2,
        "gols_pro": 23,
        "gols_contra": 13,
        "saldo_gols": 10,
        "fase_nivel": 3,
        "status": "3ª Fase"
    },
    {
        "club_id": "64223",
        "escudo_url": "https://www.cbf.com.br/_next/image?url=https%3A%2F%2Fconteudo.cbf.com.br%2Fclubes%2F64223%2Fescudo.jpg&w=256&q=70",
        "time": "Uberlândia - MG",
        "pontos": 25,
        "jogos": 13,
        "vitorias": 7,
        "empates": 4,
        "derrotas": 2,
        "gols_pro": 17,
        "gols_contra": 10,
        "saldo_gols": 7,
        "fase_nivel": 3,
        "status": "3ª Fase"
    },
    {
        "club_id": "20782",
        "escudo_url": "https://www.cbf.com.br/_next/image?url=https%3A%2F%2Fconteudo.cbf.com.br%2Fclubes%2F20782%2Fescudo.jpg&w=256&q=70",
        "time": "Aguia de Maraba - PA",
        "pontos": 24,
        "jogos": 13,
        "vitorias": 7,
        "empates": 3,
        "derrotas": 3,
        "gols_pro": 25,
        "gols_contra": 14,
        "saldo_gols": 11,
        "fase_nivel": 3,
        "status": "3ª Fase"
    },
    {
        "club_id": "20816",
        "escudo_url": "https://www.cbf.com.br/_next/image?url=https%3A%2F%2Fconteudo.cbf.com.br%2Fclubes%2F20816%2Fescudo.jpg&w=256&q=70",
        "time": "Leão do Vale - Cianorte - PR",
        "pontos": 23,
        "jogos": 14,
        "vitorias": 7,
        "empates": 2,
        "derrotas": 5,
        "gols_pro": 14,
        "gols_contra": 9,
        "saldo_gols": 5,
        "fase_nivel": 3,
        "status": "3ª Fase"
    },
    {
        "club_id": "20810",
        "escudo_url": "https://www.cbf.com.br/_next/image?url=https%3A%2F%2Fconteudo.cbf.com.br%2Fclubes%2F20810%2Fescudo.jpg&w=256&q=70",
        "time": "Trem - AP",
        "pontos": 23,
        "jogos": 13,
        "vitorias": 7,
        "empates": 2,
        "derrotas": 4,
        "gols_pro": 23,
        "gols_contra": 19,
        "saldo_gols": 4,
        "fase_nivel": 3,
        "status": "3ª Fase"
    },
    {
        "club_id": "56220",
        "escudo_url": "https://www.cbf.com.br/_next/image?url=https%3A%2F%2Fconteudo.cbf.com.br%2Fclubes%2F56220%2Fescudo.jpg&w=256&q=70",
        "time": "Gazin Porto Velho - RO",
        "pontos": 23,
        "jogos": 13,
        "vitorias": 6,
        "empates": 5,
        "derrotas": 2,
        "gols_pro": 37,
        "gols_contra": 11,
        "saldo_gols": 26,
        "fase_nivel": 3,
        "status": "3ª Fase"
    },
    {
        "club_id": "20108",
        "escudo_url": "https://www.cbf.com.br/_next/image?url=https%3A%2F%2Fconteudo.cbf.com.br%2Fclubes%2F20108%2Fescudo.jpg&w=256&q=70",
        "time": "ASA - AL",
        "pontos": 23,
        "jogos": 13,
        "vitorias": 6,
        "empates": 5,
        "derrotas": 2,
        "gols_pro": 15,
        "gols_contra": 9,
        "saldo_gols": 6,
        "fase_nivel": 3,
        "status": "3ª Fase"
    },
    {
        "club_id": "20101",
        "escudo_url": "https://www.cbf.com.br/_next/image?url=https%3A%2F%2Fconteudo.cbf.com.br%2Fclubes%2F20101%2Fescudo.jpg&w=256&q=70",
        "time": "Goiatuba - GO",
        "pontos": 23,
        "jogos": 13,
        "vitorias": 6,
        "empates": 5,
        "derrotas": 2,
        "gols_pro": 14,
        "gols_contra": 8,
        "saldo_gols": 6,
        "fase_nivel": 3,
        "status": "3ª Fase"
    },
    {
        "club_id": "21725",
        "escudo_url": "https://www.cbf.com.br/_next/image?url=https%3A%2F%2Fconteudo.cbf.com.br%2Fclubes%2F21725%2Fescudo.jpg&w=256&q=70",
        "time": "Luverdense - MT",
        "pontos": 22,
        "jogos": 13,
        "vitorias": 6,
        "empates": 4,
        "derrotas": 3,
        "gols_pro": 15,
        "gols_contra": 12,
        "saldo_gols": 3,
        "fase_nivel": 3,
        "status": "3ª Fase"
    },
    {
        "club_id": "20072",
        "escudo_url": "https://www.cbf.com.br/_next/image?url=https%3A%2F%2Fconteudo.cbf.com.br%2Fclubes%2F20072%2Fescudo.jpg&w=256&q=70",
        "time": "Xv de Piracicaba - SP",
        "pontos": 22,
        "jogos": 14,
        "vitorias": 5,
        "empates": 7,
        "derrotas": 2,
        "gols_pro": 17,
        "gols_contra": 14,
        "saldo_gols": 3,
        "fase_nivel": 3,
        "status": "3ª Fase"
    },
    {
        "club_id": "39727",
        "escudo_url": "https://www.cbf.com.br/_next/image?url=https%3A%2F%2Fconteudo.cbf.com.br%2Fclubes%2F39727%2Fescudo.jpg&w=256&q=70",
        "time": "Santa Catarina - SC",
        "pontos": 21,
        "jogos": 12,
        "vitorias": 6,
        "empates": 3,
        "derrotas": 3,
        "gols_pro": 17,
        "gols_contra": 11,
        "saldo_gols": 6,
        "fase_nivel": 2,
        "status": "2ª Fase"
    },
    {
        "club_id": "63571",
        "escudo_url": "https://www.cbf.com.br/_next/image?url=https%3A%2F%2Fconteudo.cbf.com.br%2Fclubes%2F63571%2Fescudo.jpg&w=256&q=70",
        "time": "Blumenau - SC",
        "pontos": 21,
        "jogos": 12,
        "vitorias": 6,
        "empates": 3,
        "derrotas": 3,
        "gols_pro": 16,
        "gols_contra": 10,
        "saldo_gols": 6,
        "fase_nivel": 2,
        "status": "2ª Fase"
    },
    {
        "club_id": "20071",
        "escudo_url": "https://www.cbf.com.br/_next/image?url=https%3A%2F%2Fconteudo.cbf.com.br%2Fclubes%2F20071%2Fescudo.jpg&w=256&q=70",
        "time": "Treze - PB",
        "pontos": 21,
        "jogos": 13,
        "vitorias": 6,
        "empates": 3,
        "derrotas": 4,
        "gols_pro": 22,
        "gols_contra": 17,
        "saldo_gols": 5,
        "fase_nivel": 3,
        "status": "3ª Fase"
    },
    {
        "club_id": "34709",
        "escudo_url": "https://www.cbf.com.br/_next/image?url=https%3A%2F%2Fconteudo.cbf.com.br%2Fclubes%2F34709%2Fescudo.jpg&w=256&q=70",
        "time": "Betim Futebol - MG",
        "pontos": 21,
        "jogos": 13,
        "vitorias": 6,
        "empates": 3,
        "derrotas": 4,
        "gols_pro": 15,
        "gols_contra": 10,
        "saldo_gols": 5,
        "fase_nivel": 3,
        "status": "3ª Fase"
    },
    {
        "club_id": "37846",
        "escudo_url": "https://www.cbf.com.br/_next/image?url=https%3A%2F%2Fconteudo.cbf.com.br%2Fclubes%2F37846%2Fescudo.jpg&w=256&q=70",
        "time": "Serra Branca - PB",
        "pontos": 21,
        "jogos": 13,
        "vitorias": 5,
        "empates": 6,
        "derrotas": 2,
        "gols_pro": 15,
        "gols_contra": 9,
        "saldo_gols": 6,
        "fase_nivel": 3,
        "status": "3ª Fase"
    },
    {
        "club_id": "35330",
        "escudo_url": "https://www.cbf.com.br/_next/image?url=https%3A%2F%2Fconteudo.cbf.com.br%2Fclubes%2F35330%2Fescudo.jpg&w=256&q=70",
        "time": "Maracana - CE",
        "pontos": 21,
        "jogos": 12,
        "vitorias": 5,
        "empates": 6,
        "derrotas": 1,
        "gols_pro": 13,
        "gols_contra": 7,
        "saldo_gols": 6,
        "fase_nivel": 2,
        "status": "2ª Fase"
    },
    {
        "club_id": "20207",
        "escudo_url": "https://www.cbf.com.br/_next/image?url=https%3A%2F%2Fconteudo.cbf.com.br%2Fclubes%2F20207%2Fescudo.jpg&w=256&q=70",
        "time": "Marcílio Dias - SC",
        "pontos": 21,
        "jogos": 14,
        "vitorias": 5,
        "empates": 6,
        "derrotas": 3,
        "gols_pro": 14,
        "gols_contra": 11,
        "saldo_gols": 3,
        "fase_nivel": 3,
        "status": "3ª Fase"
    },
    {
        "club_id": "20111",
        "escudo_url": "https://www.cbf.com.br/_next/image?url=https%3A%2F%2Fconteudo.cbf.com.br%2Fclubes%2F20111%2Fescudo.jpg&w=256&q=70",
        "time": "Piauí - PI",
        "pontos": 20,
        "jogos": 12,
        "vitorias": 6,
        "empates": 2,
        "derrotas": 4,
        "gols_pro": 15,
        "gols_contra": 13,
        "saldo_gols": 2,
        "fase_nivel": 2,
        "status": "2ª Fase"
    },
    {
        "club_id": "64669",
        "escudo_url": "https://www.cbf.com.br/_next/image?url=https%3A%2F%2Fconteudo.cbf.com.br%2Fclubes%2F64669%2Fescudo.jpg&w=256&q=70",
        "time": "CRAC - GO",
        "pontos": 20,
        "jogos": 13,
        "vitorias": 5,
        "empates": 5,
        "derrotas": 3,
        "gols_pro": 10,
        "gols_contra": 8,
        "saldo_gols": 2,
        "fase_nivel": 3,
        "status": "3ª Fase"
    },
    {
        "club_id": "21745",
        "escudo_url": "https://www.cbf.com.br/_next/image?url=https%3A%2F%2Fconteudo.cbf.com.br%2Fclubes%2F21745%2Fescudo.jpg&w=256&q=70",
        "time": "Araguaina - TO",
        "pontos": 19,
        "jogos": 12,
        "vitorias": 5,
        "empates": 4,
        "derrotas": 3,
        "gols_pro": 31,
        "gols_contra": 10,
        "saldo_gols": 21,
        "fase_nivel": 2,
        "status": "2ª Fase"
    },
    {
        "club_id": "31399",
        "escudo_url": "https://www.cbf.com.br/_next/image?url=https%3A%2F%2Fconteudo.cbf.com.br%2Fclubes%2F31399%2Fescudo.jpg&w=256&q=70",
        "time": "Água Santa - SP",
        "pontos": 19,
        "jogos": 12,
        "vitorias": 5,
        "empates": 4,
        "derrotas": 3,
        "gols_pro": 17,
        "gols_contra": 9,
        "saldo_gols": 8,
        "fase_nivel": 2,
        "status": "2ª Fase"
    },
    {
        "club_id": "20081",
        "escudo_url": "https://www.cbf.com.br/_next/image?url=https%3A%2F%2Fconteudo.cbf.com.br%2Fclubes%2F20081%2Fescudo.jpg&w=256&q=70",
        "time": "Vitoria - ES",
        "pontos": 18,
        "jogos": 12,
        "vitorias": 5,
        "empates": 3,
        "derrotas": 4,
        "gols_pro": 13,
        "gols_contra": 10,
        "saldo_gols": 3,
        "fase_nivel": 2,
        "status": "2ª Fase"
    },
    {
        "club_id": "20432",
        "escudo_url": "https://www.cbf.com.br/_next/image?url=https%3A%2F%2Fconteudo.cbf.com.br%2Fclubes%2F20432%2Fescudo.jpg&w=256&q=70",
        "time": "Democrata - MG",
        "pontos": 18,
        "jogos": 12,
        "vitorias": 5,
        "empates": 3,
        "derrotas": 4,
        "gols_pro": 15,
        "gols_contra": 13,
        "saldo_gols": 2,
        "fase_nivel": 2,
        "status": "2ª Fase"
    },
    {
        "club_id": "20805",
        "escudo_url": "https://www.cbf.com.br/_next/image?url=https%3A%2F%2Fconteudo.cbf.com.br%2Fclubes%2F20805%2Fescudo.jpg&w=256&q=70",
        "time": "Portuguesa - RJ",
        "pontos": 18,
        "jogos": 13,
        "vitorias": 4,
        "empates": 6,
        "derrotas": 3,
        "gols_pro": 18,
        "gols_contra": 12,
        "saldo_gols": 6,
        "fase_nivel": 3,
        "status": "3ª Fase"
    },
    {
        "club_id": "34027",
        "escudo_url": "https://www.cbf.com.br/_next/image?url=https%3A%2F%2Fconteudo.cbf.com.br%2Fclubes%2F34027%2Fescudo.jpg&w=256&q=70",
        "time": "Tombense - MG",
        "pontos": 18,
        "jogos": 12,
        "vitorias": 4,
        "empates": 6,
        "derrotas": 2,
        "gols_pro": 13,
        "gols_contra": 7,
        "saldo_gols": 6,
        "fase_nivel": 2,
        "status": "2ª Fase"
    },
    {
        "club_id": "20372",
        "escudo_url": "https://www.cbf.com.br/_next/image?url=https%3A%2F%2Fconteudo.cbf.com.br%2Fclubes%2F20372%2Fescudo.jpg&w=256&q=70",
        "time": "Imperatriz - MA",
        "pontos": 18,
        "jogos": 13,
        "vitorias": 4,
        "empates": 6,
        "derrotas": 3,
        "gols_pro": 17,
        "gols_contra": 12,
        "saldo_gols": 5,
        "fase_nivel": 3,
        "status": "3ª Fase"
    },
    {
        "club_id": "31535",
        "escudo_url": "https://www.cbf.com.br/_next/image?url=https%3A%2F%2Fconteudo.cbf.com.br%2Fclubes%2F31535%2Fescudo.jpg&w=256&q=70",
        "time": "Velo - SP",
        "pontos": 18,
        "jogos": 13,
        "vitorias": 4,
        "empates": 6,
        "derrotas": 3,
        "gols_pro": 13,
        "gols_contra": 12,
        "saldo_gols": 1,
        "fase_nivel": 3,
        "status": "3ª Fase"
    },
    {
        "club_id": "20319",
        "escudo_url": "https://www.cbf.com.br/_next/image?url=https%3A%2F%2Fconteudo.cbf.com.br%2Fclubes%2F20319%2Fescudo.jpg&w=256&q=70",
        "time": "SÃO José - SP",
        "pontos": 18,
        "jogos": 13,
        "vitorias": 4,
        "empates": 6,
        "derrotas": 3,
        "gols_pro": 9,
        "gols_contra": 10,
        "saldo_gols": -1,
        "fase_nivel": 3,
        "status": "3ª Fase"
    },
    {
        "club_id": "35212",
        "escudo_url": "https://www.cbf.com.br/_next/image?url=https%3A%2F%2Fconteudo.cbf.com.br%2Fclubes%2F35212%2Fescudo.jpg&w=256&q=70",
        "time": "Juazeirense - BA",
        "pontos": 17,
        "jogos": 12,
        "vitorias": 5,
        "empates": 2,
        "derrotas": 5,
        "gols_pro": 12,
        "gols_contra": 12,
        "saldo_gols": 0,
        "fase_nivel": 2,
        "status": "2ª Fase"
    },
    {
        "club_id": "20429",
        "escudo_url": "https://www.cbf.com.br/_next/image?url=https%3A%2F%2Fconteudo.cbf.com.br%2Fclubes%2F20429%2Fescudo.jpg&w=256&q=70",
        "time": "Parnahyba - PI",
        "pontos": 17,
        "jogos": 12,
        "vitorias": 5,
        "empates": 2,
        "derrotas": 5,
        "gols_pro": 13,
        "gols_contra": 16,
        "saldo_gols": -3,
        "fase_nivel": 2,
        "status": "2ª Fase"
    },
    {
        "club_id": "33061",
        "escudo_url": "https://www.cbf.com.br/_next/image?url=https%3A%2F%2Fconteudo.cbf.com.br%2Fclubes%2F33061%2Fescudo.jpg&w=256&q=70",
        "time": "SÃO Luiz - RS",
        "pontos": 17,
        "jogos": 13,
        "vitorias": 4,
        "empates": 5,
        "derrotas": 4,
        "gols_pro": 14,
        "gols_contra": 13,
        "saldo_gols": 1,
        "fase_nivel": 3,
        "status": "3ª Fase"
    },
    {
        "club_id": "21817",
        "escudo_url": "https://www.cbf.com.br/_next/image?url=https%3A%2F%2Fconteudo.cbf.com.br%2Fclubes%2F21817%2Fescudo.jpg&w=256&q=70",
        "time": "Ivinhema - MS",
        "pontos": 17,
        "jogos": 13,
        "vitorias": 4,
        "empates": 5,
        "derrotas": 4,
        "gols_pro": 14,
        "gols_contra": 16,
        "saldo_gols": -2,
        "fase_nivel": 3,
        "status": "3ª Fase"
    },
    {
        "club_id": "20380",
        "escudo_url": "https://www.cbf.com.br/_next/image?url=https%3A%2F%2Fconteudo.cbf.com.br%2Fclubes%2F20380%2Fescudo.jpg&w=256&q=70",
        "time": "Independência - AC",
        "pontos": 16,
        "jogos": 12,
        "vitorias": 4,
        "empates": 4,
        "derrotas": 4,
        "gols_pro": 18,
        "gols_contra": 13,
        "saldo_gols": 5,
        "fase_nivel": 2,
        "status": "2ª Fase"
    },
    {
        "club_id": "20056",
        "escudo_url": "https://www.cbf.com.br/_next/image?url=https%3A%2F%2Fconteudo.cbf.com.br%2Fclubes%2F20056%2Fescudo.jpg&w=256&q=70",
        "time": "Sampaio Corrêa - MA",
        "pontos": 16,
        "jogos": 12,
        "vitorias": 4,
        "empates": 4,
        "derrotas": 4,
        "gols_pro": 14,
        "gols_contra": 9,
        "saldo_gols": 5,
        "fase_nivel": 2,
        "status": "2ª Fase"
    },
    {
        "club_id": "21922",
        "escudo_url": "https://www.cbf.com.br/_next/image?url=https%3A%2F%2Fconteudo.cbf.com.br%2Fclubes%2F21922%2Fescudo.jpg&w=256&q=70",
        "time": "Cascavel - PR",
        "pontos": 16,
        "jogos": 12,
        "vitorias": 4,
        "empates": 4,
        "derrotas": 4,
        "gols_pro": 12,
        "gols_contra": 8,
        "saldo_gols": 4,
        "fase_nivel": 2,
        "status": "2ª Fase"
    },
    {
        "club_id": "20082",
        "escudo_url": "https://www.cbf.com.br/_next/image?url=https%3A%2F%2Fconteudo.cbf.com.br%2Fclubes%2F20082%2Fescudo.jpg&w=256&q=70",
        "time": "Noroeste - SP",
        "pontos": 16,
        "jogos": 12,
        "vitorias": 4,
        "empates": 4,
        "derrotas": 4,
        "gols_pro": 14,
        "gols_contra": 11,
        "saldo_gols": 3,
        "fase_nivel": 2,
        "status": "2ª Fase"
    },
    {
        "club_id": "59116",
        "escudo_url": "https://www.cbf.com.br/_next/image?url=https%3A%2F%2Fconteudo.cbf.com.br%2Fclubes%2F59116%2Fescudo.jpg&w=256&q=70",
        "time": "Maguary - PE",
        "pontos": 16,
        "jogos": 13,
        "vitorias": 4,
        "empates": 4,
        "derrotas": 5,
        "gols_pro": 12,
        "gols_contra": 9,
        "saldo_gols": 3,
        "fase_nivel": 3,
        "status": "3ª Fase"
    },
    {
        "club_id": "20034",
        "escudo_url": "https://www.cbf.com.br/_next/image?url=https%3A%2F%2Fconteudo.cbf.com.br%2Fclubes%2F20034%2Fescudo.jpg&w=256&q=70",
        "time": "Sergipe - SE",
        "pontos": 16,
        "jogos": 12,
        "vitorias": 4,
        "empates": 4,
        "derrotas": 4,
        "gols_pro": 16,
        "gols_contra": 15,
        "saldo_gols": 1,
        "fase_nivel": 2,
        "status": "2ª Fase"
    },
    {
        "club_id": "54488",
        "escudo_url": "https://www.cbf.com.br/_next/image?url=https%3A%2F%2Fconteudo.cbf.com.br%2Fclubes%2F54488%2Fescudo.jpg&w=256&q=70",
        "time": "Sãojoseense - PR",
        "pontos": 16,
        "jogos": 12,
        "vitorias": 4,
        "empates": 4,
        "derrotas": 4,
        "gols_pro": 4,
        "gols_contra": 5,
        "saldo_gols": -1,
        "fase_nivel": 2,
        "status": "2ª Fase"
    },
    {
        "club_id": "20076",
        "escudo_url": "https://www.cbf.com.br/_next/image?url=https%3A%2F%2Fconteudo.cbf.com.br%2Fclubes%2F20076%2Fescudo.jpg&w=256&q=70",
        "time": "Joinville - SC",
        "pontos": 15,
        "jogos": 10,
        "vitorias": 4,
        "empates": 3,
        "derrotas": 3,
        "gols_pro": 10,
        "gols_contra": 8,
        "saldo_gols": 2,
        "fase_nivel": 1,
        "status": "1ª Fase"
    },
    {
        "club_id": "21638",
        "escudo_url": "https://www.cbf.com.br/_next/image?url=https%3A%2F%2Fconteudo.cbf.com.br%2Fclubes%2F21638%2Fescudo.jpg&w=256&q=70",
        "time": "SÃO Raimundo - RR",
        "pontos": 15,
        "jogos": 12,
        "vitorias": 3,
        "empates": 6,
        "derrotas": 3,
        "gols_pro": 12,
        "gols_contra": 9,
        "saldo_gols": 3,
        "fase_nivel": 2,
        "status": "2ª Fase"
    },
    {
        "club_id": "62652",
        "escudo_url": "https://www.cbf.com.br/_next/image?url=https%3A%2F%2Fconteudo.cbf.com.br%2Fclubes%2F62652%2Fescudo.jpg&w=256&q=70",
        "time": "Brasiliense - DF",
        "pontos": 15,
        "jogos": 12,
        "vitorias": 3,
        "empates": 6,
        "derrotas": 3,
        "gols_pro": 11,
        "gols_contra": 11,
        "saldo_gols": 0,
        "fase_nivel": 2,
        "status": "2ª Fase"
    },
    {
        "club_id": "62546",
        "escudo_url": "https://www.cbf.com.br/_next/image?url=https%3A%2F%2Fconteudo.cbf.com.br%2Fclubes%2F62546%2Fescudo.jpg&w=256&q=70",
        "time": "RIO Branco - AC",
        "pontos": 14,
        "jogos": 12,
        "vitorias": 3,
        "empates": 5,
        "derrotas": 4,
        "gols_pro": 16,
        "gols_contra": 16,
        "saldo_gols": 0,
        "fase_nivel": 2,
        "status": "2ª Fase"
    },
    {
        "club_id": "35775",
        "escudo_url": "https://www.cbf.com.br/_next/image?url=https%3A%2F%2Fconteudo.cbf.com.br%2Fclubes%2F35775%2Fescudo.jpg&w=256&q=70",
        "time": "Fluminense - PI",
        "pontos": 14,
        "jogos": 12,
        "vitorias": 3,
        "empates": 5,
        "derrotas": 4,
        "gols_pro": 12,
        "gols_contra": 13,
        "saldo_gols": -1,
        "fase_nivel": 2,
        "status": "2ª Fase"
    },
    {
        "club_id": "20112",
        "escudo_url": "https://www.cbf.com.br/_next/image?url=https%3A%2F%2Fconteudo.cbf.com.br%2Fclubes%2F20112%2Fescudo.jpg&w=256&q=70",
        "time": "Central de Caruaru - PE",
        "pontos": 14,
        "jogos": 12,
        "vitorias": 3,
        "empates": 5,
        "derrotas": 4,
        "gols_pro": 9,
        "gols_contra": 10,
        "saldo_gols": -1,
        "fase_nivel": 2,
        "status": "2ª Fase"
    },
    {
        "club_id": "35680",
        "escudo_url": "https://www.cbf.com.br/_next/image?url=https%3A%2F%2Fconteudo.cbf.com.br%2Fclubes%2F35680%2Fescudo.jpg&w=256&q=70",
        "time": "Lagarto - SE",
        "pontos": 14,
        "jogos": 12,
        "vitorias": 3,
        "empates": 5,
        "derrotas": 4,
        "gols_pro": 15,
        "gols_contra": 18,
        "saldo_gols": -3,
        "fase_nivel": 2,
        "status": "2ª Fase"
    },
    {
        "club_id": "21889",
        "escudo_url": "https://www.cbf.com.br/_next/image?url=https%3A%2F%2Fconteudo.cbf.com.br%2Fclubes%2F21889%2Fescudo.jpg&w=256&q=70",
        "time": "Aparecidense - GO",
        "pontos": 14,
        "jogos": 12,
        "vitorias": 3,
        "empates": 5,
        "derrotas": 4,
        "gols_pro": 14,
        "gols_contra": 17,
        "saldo_gols": -3,
        "fase_nivel": 2,
        "status": "2ª Fase"
    },
    {
        "club_id": "20100",
        "escudo_url": "https://www.cbf.com.br/_next/image?url=https%3A%2F%2Fconteudo.cbf.com.br%2Fclubes%2F20100%2Fescudo.jpg&w=256&q=70",
        "time": "Tuna Luso - PA",
        "pontos": 14,
        "jogos": 12,
        "vitorias": 3,
        "empates": 5,
        "derrotas": 4,
        "gols_pro": 16,
        "gols_contra": 20,
        "saldo_gols": -4,
        "fase_nivel": 2,
        "status": "2ª Fase"
    },
    {
        "club_id": "35152",
        "escudo_url": "https://www.cbf.com.br/_next/image?url=https%3A%2F%2Fconteudo.cbf.com.br%2Fclubes%2F35152%2Fescudo.jpg&w=256&q=70",
        "time": "Jacuipense - BA",
        "pontos": 14,
        "jogos": 12,
        "vitorias": 3,
        "empates": 5,
        "derrotas": 4,
        "gols_pro": 13,
        "gols_contra": 17,
        "saldo_gols": -4,
        "fase_nivel": 2,
        "status": "2ª Fase"
    },
    {
        "club_id": "63519",
        "escudo_url": "https://www.cbf.com.br/_next/image?url=https%3A%2F%2Fconteudo.cbf.com.br%2Fclubes%2F63519%2Fescudo.jpg&w=256&q=70",
        "time": "Ceilândia - DF",
        "pontos": 13,
        "jogos": 12,
        "vitorias": 3,
        "empates": 4,
        "derrotas": 5,
        "gols_pro": 11,
        "gols_contra": 13,
        "saldo_gols": -2,
        "fase_nivel": 2,
        "status": "2ª Fase"
    },
    {
        "club_id": "32387",
        "escudo_url": "https://www.cbf.com.br/_next/image?url=https%3A%2F%2Fconteudo.cbf.com.br%2Fclubes%2F32387%2Fescudo.jpg&w=256&q=70",
        "time": "Sampaio Correa - RJ",
        "pontos": 13,
        "jogos": 12,
        "vitorias": 3,
        "empates": 4,
        "derrotas": 5,
        "gols_pro": 9,
        "gols_contra": 12,
        "saldo_gols": -3,
        "fase_nivel": 2,
        "status": "2ª Fase"
    },
    {
        "club_id": "62190",
        "escudo_url": "https://www.cbf.com.br/_next/image?url=https%3A%2F%2Fconteudo.cbf.com.br%2Fclubes%2F62190%2Fescudo.jpg&w=256&q=70",
        "time": "Monte Roraima - RR",
        "pontos": 13,
        "jogos": 12,
        "vitorias": 3,
        "empates": 4,
        "derrotas": 5,
        "gols_pro": 14,
        "gols_contra": 18,
        "saldo_gols": -4,
        "fase_nivel": 2,
        "status": "2ª Fase"
    },
    {
        "club_id": "20046",
        "escudo_url": "https://www.cbf.com.br/_next/image?url=https%3A%2F%2Fconteudo.cbf.com.br%2Fclubes%2F20046%2Fescudo.jpg&w=256&q=70",
        "time": "América - RN",
        "pontos": 13,
        "jogos": 12,
        "vitorias": 3,
        "empates": 4,
        "derrotas": 5,
        "gols_pro": 12,
        "gols_contra": 24,
        "saldo_gols": -12,
        "fase_nivel": 2,
        "status": "2ª Fase"
    },
    {
        "club_id": "20288",
        "escudo_url": "https://www.cbf.com.br/_next/image?url=https%3A%2F%2Fconteudo.cbf.com.br%2Fclubes%2F20288%2Fescudo.jpg&w=256&q=70",
        "time": "Tocantinopolis - TO",
        "pontos": 12,
        "jogos": 10,
        "vitorias": 3,
        "empates": 3,
        "derrotas": 4,
        "gols_pro": 18,
        "gols_contra": 18,
        "saldo_gols": 0,
        "fase_nivel": 1,
        "status": "1ª Fase"
    },
    {
        "club_id": "63665",
        "escudo_url": "https://www.cbf.com.br/_next/image?url=https%3A%2F%2Fconteudo.cbf.com.br%2Fclubes%2F63665%2Fescudo.jpg&w=256&q=70",
        "time": "Abecat - GO",
        "pontos": 12,
        "jogos": 10,
        "vitorias": 3,
        "empates": 3,
        "derrotas": 4,
        "gols_pro": 8,
        "gols_contra": 9,
        "saldo_gols": -1,
        "fase_nivel": 1,
        "status": "1ª Fase"
    },
    {
        "club_id": "55531",
        "escudo_url": "https://www.cbf.com.br/_next/image?url=https%3A%2F%2Fconteudo.cbf.com.br%2Fclubes%2F55531%2Fescudo.jpg&w=256&q=70",
        "time": "Retrô - PE",
        "pontos": 12,
        "jogos": 10,
        "vitorias": 3,
        "empates": 3,
        "derrotas": 4,
        "gols_pro": 13,
        "gols_contra": 15,
        "saldo_gols": -2,
        "fase_nivel": 1,
        "status": "1ª Fase"
    },
    {
        "club_id": "59905",
        "escudo_url": "https://www.cbf.com.br/_next/image?url=https%3A%2F%2Fconteudo.cbf.com.br%2Fclubes%2F59905%2Fescudo.jpg&w=256&q=70",
        "time": "Primavera Atlético - SP",
        "pontos": 12,
        "jogos": 10,
        "vitorias": 3,
        "empates": 3,
        "derrotas": 4,
        "gols_pro": 10,
        "gols_contra": 13,
        "saldo_gols": -3,
        "fase_nivel": 1,
        "status": "1ª Fase"
    },
    {
        "club_id": "64287",
        "escudo_url": "https://www.cbf.com.br/_next/image?url=https%3A%2F%2Fconteudo.cbf.com.br%2Fclubes%2F64287%2Fescudo.jpg&w=256&q=70",
        "time": "Nova Iguaçu - RJ",
        "pontos": 12,
        "jogos": 10,
        "vitorias": 3,
        "empates": 3,
        "derrotas": 4,
        "gols_pro": 7,
        "gols_contra": 10,
        "saldo_gols": -3,
        "fase_nivel": 1,
        "status": "1ª Fase"
    },
    {
        "club_id": "53914",
        "escudo_url": "https://www.cbf.com.br/_next/image?url=https%3A%2F%2Fconteudo.cbf.com.br%2Fclubes%2F53914%2Fescudo.jpg&w=256&q=70",
        "time": "Altos - PI",
        "pontos": 12,
        "jogos": 12,
        "vitorias": 3,
        "empates": 3,
        "derrotas": 6,
        "gols_pro": 10,
        "gols_contra": 17,
        "saldo_gols": -7,
        "fase_nivel": 2,
        "status": "2ª Fase"
    },
    {
        "club_id": "20064",
        "escudo_url": "https://www.cbf.com.br/_next/image?url=https%3A%2F%2Fconteudo.cbf.com.br%2Fclubes%2F20064%2Fescudo.jpg&w=256&q=70",
        "time": "Mixto - MT",
        "pontos": 12,
        "jogos": 12,
        "vitorias": 2,
        "empates": 6,
        "derrotas": 4,
        "gols_pro": 11,
        "gols_contra": 12,
        "saldo_gols": -1,
        "fase_nivel": 2,
        "status": "2ª Fase"
    },
    {
        "club_id": "20249",
        "escudo_url": "https://www.cbf.com.br/_next/image?url=https%3A%2F%2Fconteudo.cbf.com.br%2Fclubes%2F20249%2Fescudo.jpg&w=256&q=70",
        "time": "Madureira - RJ",
        "pontos": 11,
        "jogos": 10,
        "vitorias": 3,
        "empates": 2,
        "derrotas": 5,
        "gols_pro": 11,
        "gols_contra": 16,
        "saldo_gols": -5,
        "fase_nivel": 1,
        "status": "1ª Fase"
    },
    {
        "club_id": "32036",
        "escudo_url": "https://www.cbf.com.br/_next/image?url=https%3A%2F%2Fconteudo.cbf.com.br%2Fclubes%2F32036%2Fescudo.jpg&w=256&q=70",
        "time": "Marica - RJ",
        "pontos": 11,
        "jogos": 10,
        "vitorias": 3,
        "empates": 2,
        "derrotas": 5,
        "gols_pro": 9,
        "gols_contra": 14,
        "saldo_gols": -5,
        "fase_nivel": 1,
        "status": "1ª Fase"
    },
    {
        "club_id": "20390",
        "escudo_url": "https://www.cbf.com.br/_next/image?url=https%3A%2F%2Fconteudo.cbf.com.br%2Fclubes%2F20390%2Fescudo.jpg&w=256&q=70",
        "time": "Sousa - PB",
        "pontos": 10,
        "jogos": 10,
        "vitorias": 3,
        "empates": 1,
        "derrotas": 6,
        "gols_pro": 4,
        "gols_contra": 11,
        "saldo_gols": -7,
        "fase_nivel": 1,
        "status": "1ª Fase"
    },
    {
        "club_id": "62328",
        "escudo_url": "https://www.cbf.com.br/_next/image?url=https%3A%2F%2Fconteudo.cbf.com.br%2Fclubes%2F62328%2Fescudo.jpg&w=256&q=70",
        "time": "Porto - BA",
        "pontos": 10,
        "jogos": 10,
        "vitorias": 3,
        "empates": 1,
        "derrotas": 6,
        "gols_pro": 9,
        "gols_contra": 21,
        "saldo_gols": -12,
        "fase_nivel": 1,
        "status": "1ª Fase"
    },
    {
        "club_id": "32816",
        "escudo_url": "https://www.cbf.com.br/_next/image?url=https%3A%2F%2Fconteudo.cbf.com.br%2Fclubes%2F32816%2Fescudo.jpg&w=256&q=70",
        "time": "Galvez - AC",
        "pontos": 10,
        "jogos": 10,
        "vitorias": 3,
        "empates": 1,
        "derrotas": 6,
        "gols_pro": 14,
        "gols_contra": 31,
        "saldo_gols": -17,
        "fase_nivel": 1,
        "status": "1ª Fase"
    },
    {
        "club_id": "62217",
        "escudo_url": "https://www.cbf.com.br/_next/image?url=https%3A%2F%2Fconteudo.cbf.com.br%2Fclubes%2F62217%2Fescudo.jpg&w=256&q=70",
        "time": "Tirol - CE",
        "pontos": 10,
        "jogos": 10,
        "vitorias": 2,
        "empates": 4,
        "derrotas": 4,
        "gols_pro": 10,
        "gols_contra": 10,
        "saldo_gols": 0,
        "fase_nivel": 1,
        "status": "1ª Fase"
    },
    {
        "club_id": "64810",
        "escudo_url": "https://www.cbf.com.br/_next/image?url=https%3A%2F%2Fconteudo.cbf.com.br%2Fclubes%2F64810%2Fescudo.jpg&w=256&q=70",
        "time": "Gremio Esportivo Brasil - RS",
        "pontos": 10,
        "jogos": 10,
        "vitorias": 2,
        "empates": 4,
        "derrotas": 4,
        "gols_pro": 9,
        "gols_contra": 12,
        "saldo_gols": -3,
        "fase_nivel": 1,
        "status": "1ª Fase"
    },
    {
        "club_id": "52844",
        "escudo_url": "https://www.cbf.com.br/_next/image?url=https%3A%2F%2Fconteudo.cbf.com.br%2Fclubes%2F52844%2Fescudo.jpg&w=256&q=70",
        "time": "Manaus - AM",
        "pontos": 10,
        "jogos": 10,
        "vitorias": 2,
        "empates": 4,
        "derrotas": 4,
        "gols_pro": 8,
        "gols_contra": 13,
        "saldo_gols": -5,
        "fase_nivel": 1,
        "status": "1ª Fase"
    },
    {
        "club_id": "20041",
        "escudo_url": "https://www.cbf.com.br/_next/image?url=https%3A%2F%2Fconteudo.cbf.com.br%2Fclubes%2F20041%2Fescudo.jpg&w=256&q=70",
        "time": "Operário - MS",
        "pontos": 9,
        "jogos": 10,
        "vitorias": 2,
        "empates": 3,
        "derrotas": 5,
        "gols_pro": 9,
        "gols_contra": 12,
        "saldo_gols": -3,
        "fase_nivel": 1,
        "status": "1ª Fase"
    },
    {
        "club_id": "56804",
        "escudo_url": "https://www.cbf.com.br/_next/image?url=https%3A%2F%2Fconteudo.cbf.com.br%2Fclubes%2F56804%2Fescudo.jpg&w=256&q=70",
        "time": "Azuriz - PR",
        "pontos": 9,
        "jogos": 10,
        "vitorias": 2,
        "empates": 3,
        "derrotas": 5,
        "gols_pro": 7,
        "gols_contra": 11,
        "saldo_gols": -4,
        "fase_nivel": 1,
        "status": "1ª Fase"
    },
    {
        "club_id": "20287",
        "escudo_url": "https://www.cbf.com.br/_next/image?url=https%3A%2F%2Fconteudo.cbf.com.br%2Fclubes%2F20287%2Fescudo.jpg&w=256&q=70",
        "time": "União - MT",
        "pontos": 9,
        "jogos": 10,
        "vitorias": 2,
        "empates": 3,
        "derrotas": 5,
        "gols_pro": 11,
        "gols_contra": 18,
        "saldo_gols": -7,
        "fase_nivel": 1,
        "status": "1ª Fase"
    },
    {
        "club_id": "35522",
        "escudo_url": "https://www.cbf.com.br/_next/image?url=https%3A%2F%2Fconteudo.cbf.com.br%2Fclubes%2F35522%2Fescudo.jpg&w=256&q=70",
        "time": "CSE - AL",
        "pontos": 9,
        "jogos": 10,
        "vitorias": 2,
        "empates": 3,
        "derrotas": 5,
        "gols_pro": 10,
        "gols_contra": 17,
        "saldo_gols": -7,
        "fase_nivel": 1,
        "status": "1ª Fase"
    },
    {
        "club_id": "20029",
        "escudo_url": "https://www.cbf.com.br/_next/image?url=https%3A%2F%2Fconteudo.cbf.com.br%2Fclubes%2F20029%2Fescudo.jpg&w=256&q=70",
        "time": "Moto Club - MA",
        "pontos": 9,
        "jogos": 10,
        "vitorias": 2,
        "empates": 3,
        "derrotas": 5,
        "gols_pro": 8,
        "gols_contra": 15,
        "saldo_gols": -7,
        "fase_nivel": 1,
        "status": "1ª Fase"
    },
    {
        "club_id": "35768",
        "escudo_url": "https://www.cbf.com.br/_next/image?url=https%3A%2F%2Fconteudo.cbf.com.br%2Fclubes%2F35768%2Fescudo.jpg&w=256&q=70",
        "time": "Decisão - PE",
        "pontos": 8,
        "jogos": 10,
        "vitorias": 2,
        "empates": 2,
        "derrotas": 6,
        "gols_pro": 10,
        "gols_contra": 17,
        "saldo_gols": -7,
        "fase_nivel": 1,
        "status": "1ª Fase"
    },
    {
        "club_id": "21942",
        "escudo_url": "https://www.cbf.com.br/_next/image?url=https%3A%2F%2Fconteudo.cbf.com.br%2Fclubes%2F21942%2Fescudo.jpg&w=256&q=70",
        "time": "Real Noroeste Capixaba - ES",
        "pontos": 8,
        "jogos": 10,
        "vitorias": 1,
        "empates": 5,
        "derrotas": 4,
        "gols_pro": 6,
        "gols_contra": 11,
        "saldo_gols": -5,
        "fase_nivel": 1,
        "status": "1ª Fase"
    },
    {
        "club_id": "63322",
        "escudo_url": "https://www.cbf.com.br/_next/image?url=https%3A%2F%2Fconteudo.cbf.com.br%2Fclubes%2F63322%2Fescudo.jpg&w=256&q=70",
        "time": "Pouso Alegre - MG",
        "pontos": 7,
        "jogos": 10,
        "vitorias": 2,
        "empates": 1,
        "derrotas": 7,
        "gols_pro": 6,
        "gols_contra": 14,
        "saldo_gols": -8,
        "fase_nivel": 1,
        "status": "1ª Fase"
    },
    {
        "club_id": "35316",
        "escudo_url": "https://www.cbf.com.br/_next/image?url=https%3A%2F%2Fconteudo.cbf.com.br%2Fclubes%2F35316%2Fescudo.jpg&w=256&q=70",
        "time": "Atlético Cearense - CE",
        "pontos": 7,
        "jogos": 10,
        "vitorias": 1,
        "empates": 4,
        "derrotas": 5,
        "gols_pro": 6,
        "gols_contra": 14,
        "saldo_gols": -8,
        "fase_nivel": 1,
        "status": "1ª Fase"
    },
    {
        "club_id": "20353",
        "escudo_url": "https://www.cbf.com.br/_next/image?url=https%3A%2F%2Fconteudo.cbf.com.br%2Fclubes%2F20353%2Fescudo.jpg&w=256&q=70",
        "time": "Sampaio - RR",
        "pontos": 5,
        "jogos": 10,
        "vitorias": 1,
        "empates": 2,
        "derrotas": 7,
        "gols_pro": 8,
        "gols_contra": 17,
        "saldo_gols": -9,
        "fase_nivel": 1,
        "status": "1ª Fase"
    },
    {
        "club_id": "35079",
        "escudo_url": "https://www.cbf.com.br/_next/image?url=https%3A%2F%2Fconteudo.cbf.com.br%2Fclubes%2F35079%2Fescudo.jpg&w=256&q=70",
        "time": "Operário - MT",
        "pontos": 5,
        "jogos": 10,
        "vitorias": 1,
        "empates": 2,
        "derrotas": 7,
        "gols_pro": 7,
        "gols_contra": 16,
        "saldo_gols": -9,
        "fase_nivel": 1,
        "status": "1ª Fase"
    },
    {
        "club_id": "20236",
        "escudo_url": "https://www.cbf.com.br/_next/image?url=https%3A%2F%2Fconteudo.cbf.com.br%2Fclubes%2F20236%2Fescudo.jpg&w=256&q=70",
        "time": "Atlético de Alagoinhas - BA",
        "pontos": 5,
        "jogos": 10,
        "vitorias": 1,
        "empates": 2,
        "derrotas": 7,
        "gols_pro": 5,
        "gols_contra": 20,
        "saldo_gols": -15,
        "fase_nivel": 1,
        "status": "1ª Fase"
    },
    {
        "club_id": "20225",
        "escudo_url": "https://www.cbf.com.br/_next/image?url=https%3A%2F%2Fconteudo.cbf.com.br%2Fclubes%2F20225%2Fescudo.jpg&w=256&q=70",
        "time": "Guarany - CE",
        "pontos": 4,
        "jogos": 10,
        "vitorias": 1,
        "empates": 1,
        "derrotas": 8,
        "gols_pro": 2,
        "gols_contra": 18,
        "saldo_gols": -16,
        "fase_nivel": 1,
        "status": "1ª Fase"
    },
    {
        "club_id": "21829",
        "escudo_url": "https://www.cbf.com.br/_next/image?url=https%3A%2F%2Fconteudo.cbf.com.br%2Fclubes%2F21829%2Fescudo.jpg&w=256&q=70",
        "time": "Oratório - AP",
        "pontos": 4,
        "jogos": 10,
        "vitorias": 1,
        "empates": 1,
        "derrotas": 8,
        "gols_pro": 12,
        "gols_contra": 29,
        "saldo_gols": -17,
        "fase_nivel": 1,
        "status": "1ª Fase"
    },
    {
        "club_id": "21894",
        "escudo_url": "https://www.cbf.com.br/_next/image?url=https%3A%2F%2Fconteudo.cbf.com.br%2Fclubes%2F21894%2Fescudo.jpg&w=256&q=70",
        "time": "Iape - MA",
        "pontos": 4,
        "jogos": 10,
        "vitorias": 0,
        "empates": 4,
        "derrotas": 6,
        "gols_pro": 10,
        "gols_contra": 20,
        "saldo_gols": -10,
        "fase_nivel": 1,
        "status": "1ª Fase"
    },
    {
        "club_id": "60415",
        "escudo_url": "https://www.cbf.com.br/_next/image?url=https%3A%2F%2Fconteudo.cbf.com.br%2Fclubes%2F60415%2Fescudo.jpg&w=256&q=70",
        "time": "Laguna - RN",
        "pontos": 2,
        "jogos": 10,
        "vitorias": 0,
        "empates": 2,
        "derrotas": 8,
        "gols_pro": 3,
        "gols_contra": 20,
        "saldo_gols": -17,
        "fase_nivel": 1,
        "status": "1ª Fase"
    },
    {
        "club_id": "37539",
        "escudo_url": "https://www.cbf.com.br/_next/image?url=https%3A%2F%2Fconteudo.cbf.com.br%2Fclubes%2F37539%2Fescudo.jpg&w=256&q=70",
        "time": "Inhumas - GO",
        "pontos": 1,
        "jogos": 10,
        "vitorias": 0,
        "empates": 1,
        "derrotas": 9,
        "gols_pro": 3,
        "gols_contra": 20,
        "saldo_gols": -17,
        "fase_nivel": 1,
        "status": "1ª Fase"
    },
    {
        "club_id": "54133",
        "escudo_url": "https://www.cbf.com.br/_next/image?url=https%3A%2F%2Fconteudo.cbf.com.br%2Fclubes%2F54133%2Fescudo.jpg&w=256&q=70",
        "time": "Humaitá - AC",
        "pontos": 0,
        "jogos": 10,
        "vitorias": 0,
        "empates": 0,
        "derrotas": 10,
        "gols_pro": 4,
        "gols_contra": 50,
        "saldo_gols": -46,
        "fase_nivel": 1,
        "status": "1ª Fase"
    }
]